openreward/__init__.py
openreward/cli.py
openreward/client.py
openreward/http_client.py
openreward/models.py
openreward/api/__init__.py
openreward/api/environments/__init__.py
openreward/api/environments/client.py
openreward/api/environments/http.py
openreward/api/environments/ping.py
openreward/api/environments/types.py
openreward/api/rollouts/__init__.py
openreward/api/rollouts/background.py
openreward/api/rollouts/rollout.py
openreward/api/rollouts/serializers/__init__.py
openreward/api/rollouts/serializers/ant.py
openreward/api/rollouts/serializers/base.py
openreward/api/rollouts/serializers/gdm.py
openreward/api/rollouts/serializers/models.py
openreward/api/rollouts/serializers/oai_completions.py
openreward/api/rollouts/serializers/oai_responses.py
openreward/api/rollouts/serializers/utils.py
openreward/api/sandboxes/__init__.py
openreward/api/sandboxes/client.py
openreward/api/sandboxes/http.py
openreward/api/sandboxes/ping.py
openreward/api/sandboxes/types.py
openreward/environments/__init__.py
openreward/environments/environment.py
openreward/environments/reconnect.py
openreward/environments/server.py
openreward/environments/toolset.py
openreward/environments/types.py
openreward/environments/utils.py
openreward/templates/__init__.py
openreward/templates/basic/Dockerfile
openreward/templates/basic/__init__.py
openreward/templates/basic/requirements.txt
openreward/templates/basic/requirements.txt.tmpl
openreward/templates/basic/server.py.tmpl
openreward/templates/sandbox/Dockerfile
openreward/templates/sandbox/__init__.py
openreward/templates/sandbox/requirements.txt
openreward/templates/sandbox/sandbox_env.py
openreward/templates/sandbox/server.py
openreward/toolsets/__init__.py
openreward/toolsets/pdf.py
openreward/toolsets/word.py
openreward-0.1.21.dist-info/METADATA
openreward-0.1.21.dist-info/WHEEL
openreward-0.1.21.dist-info/entry_points.txt
openreward-0.1.21.dist-info/top_level.txt
openreward-0.1.21.dist-info/RECORD
