Metadata-Version: 2.4
Name: openreward
Version: 0.1.21
Summary: Python SDK for OpenrReward tracing and logging
Author-email: Kip Parker <kip@gr.inc>, Thomas Grady <thomas@gr.inc>
Requires-Dist: aiohttp>=3.13.2
Requires-Dist: anthropic>=0.69.0
Requires-Dist: google-genai>=1.4.0
Requires-Dist: openai>=1.88.0
Requires-Dist: tenacity>=9.1.2
Requires-Dist: fastapi>=0.115.12
Requires-Dist: pydantic>=2.11.5
Requires-Dist: sse-starlette==2.3.6
Requires-Dist: uvicorn>=0.34.3
Requires-Dist: typing-extensions>=4.9.0
Provides-Extra: dev
Requires-Dist: pytest>=7.0.0; extra == "dev"
Requires-Dist: pytest-asyncio>=0.21.0; extra == "dev"
Requires-Dist: pytest-cov>=4.0.0; extra == "dev"
Requires-Dist: black>=23.0.0; extra == "dev"
Requires-Dist: mypy>=1.0.0; extra == "dev"
Requires-Dist: ruff>=0.1.0; extra == "dev"
